MANIFEST.in
README.md
setup.py
piepd/__init__.py
piepd/epd.py
piepd/fonts.py
piepd.egg-info/PKG-INFO
piepd.egg-info/SOURCES.txt
piepd.egg-info/dependency_links.txt
piepd.egg-info/entry_points.txt
piepd.egg-info/requires.txt
piepd.egg-info/top_level.txt
piepd/fonts/nova/NovaMono-Regular.ttf
piepd/waveshare_epd/__init__.py
piepd/waveshare_epd/epd1in02.py
piepd/waveshare_epd/epd1in54.py
piepd/waveshare_epd/epd1in54_V2.py
piepd/waveshare_epd/epd1in54b.py
piepd/waveshare_epd/epd1in54b_V2.py
piepd/waveshare_epd/epd1in54c.py
piepd/waveshare_epd/epd2in13.py
piepd/waveshare_epd/epd2in13_V2.py
piepd/waveshare_epd/epd2in13b_V3.py
piepd/waveshare_epd/epd2in13bc.py
piepd/waveshare_epd/epd2in13d.py
piepd/waveshare_epd/epd2in66.py
piepd/waveshare_epd/epd2in7.py
piepd/waveshare_epd/epd2in7b.py
piepd/waveshare_epd/epd2in9.py
piepd/waveshare_epd/epd2in9b_V2.py
piepd/waveshare_epd/epd2in9bc.py
piepd/waveshare_epd/epd2in9d.py
piepd/waveshare_epd/epd3in7.py
piepd/waveshare_epd/epd4in2.py
piepd/waveshare_epd/epd4in2b_V2.py
piepd/waveshare_epd/epd4in2bc.py
piepd/waveshare_epd/epd5in65f.py
piepd/waveshare_epd/epd5in83.py
piepd/waveshare_epd/epd5in83b_V2.py
piepd/waveshare_epd/epd5in83bc.py
piepd/waveshare_epd/epd7in5.py
piepd/waveshare_epd/epd7in5_HD.py
piepd/waveshare_epd/epd7in5_V2.py
piepd/waveshare_epd/epd7in5b_HD.py
piepd/waveshare_epd/epd7in5bc.py
piepd/waveshare_epd/epd7in5bc_V2.py
piepd/waveshare_epd/epdconfig.py