Metadata-Version: 2.1
Name: piepd
Version: 0.0.3.5
Summary: High level ePaper display utilty
Home-page: https://github.com/Tsangares/epd
Author-email: william.wyatt@cgu.edu
License: UNKNOWN
Platform: UNKNOWN
Classifier: Programming Language :: Python :: 3
Classifier: License :: OSI Approved :: MIT License
Classifier: Operating System :: OS Independent
Requires-Python: >=3.7
